[
    {
        "id": 1,
        "rfrom": "*",
        "rto": "index.html",
        "name": "Home",
        "parent": ""
    },
    {
        "id": 10,
        "rfrom": "*",
        "rto": "notifications.html",
        "name": "Notifications",
        "parent": ""
    },
    {
        "id": 20,
        "rfrom": "*",
        "rto": "history.html",
        "name": "History",
        "parent": ""
    },
    {
        "id": 21,
        "rfrom": "*",
        "rto": "#",
        "name": "Analytics",
        "parent": ""
    },
    {
        "id": 40,
        "rfrom": "*",
        "rto": "#",
        "name": "Settings",
        "parent": ""
    }
]